basic_maths_011/__init__.py
basic_maths_011/advanced_calculations.py
basic_maths_011/basic_calculations.py
basic_maths_011-0.3.dist-info/LICENSE
basic_maths_011-0.3.dist-info/METADATA
basic_maths_011-0.3.dist-info/WHEEL
basic_maths_011-0.3.dist-info/top_level.txt
basic_maths_011-0.3.dist-info/RECORD
