Metadata-Version: 2.1
Name: basic-maths-011
Version: 0.3
Summary: A simple maths package
Home-page: 
Author: Mahesh A R
Author-email: amaheshar@gmail.com
Classifier: Programming Language :: Python :: 3
Classifier: Operating System :: OS Independent
Requires-Python: >=3.6
License-File: LICENSE
